emrap/__init__.py
emrap/common.py
emrap/extracts.py
emrap/gmail.py
emrap/http.py
emrap/messages.py
emrap/utils.py
emrap/actions/__init__.py
emrap/actions/common.py
emrap/actions/http.py
emrap-1.0.post1.dist-info/LICENSE
emrap-1.0.post1.dist-info/METADATA
emrap-1.0.post1.dist-info/WHEEL
emrap-1.0.post1.dist-info/top_level.txt
emrap-1.0.post1.dist-info/RECORD
