Metadata-Version: 2.1
Name: emrap
Version: 1.0.post1
Summary: eMail Requestor and Processor
Home-page: https://github.com/aayla-secura/eMRaP
Author: AaylaSecura1138
Author-email: aayla.secura.1138@gmail.com
License: UNKNOWN
Platform: UNKNOWN
Classifier: Programming Language :: Python :: 3.6
Classifier: Programming Language :: Python :: 3.7
Classifier: Programming Language :: Python :: 3.8
Classifier: Programming Language :: Python :: 3.9
Classifier: License :: OSI Approved :: MIT License
Classifier: Operating System :: OS Independent
Requires-Dist: google-api-python-client
Requires-Dist: google-auth-httplib2
Requires-Dist: google-auth-oauthlib
Requires-Dist: http-parser
Requires-Dist: requests
Requires-Dist: colorlog
